automa/bot/__init__.py
automa/bot/_base_client.py
automa/bot/_client.py
automa/bot/_resource.py
automa/bot/_types.py
automa/bot/webhook.py
automa/bot/resources/__init__.py
automa/bot/resources/code.py
automa_bot-0.2.3.dist-info/METADATA
automa_bot-0.2.3.dist-info/WHEEL
automa_bot-0.2.3.dist-info/top_level.txt
automa_bot-0.2.3.dist-info/RECORD
