Metadata-Version: 2.4
Name: automa-bot
Version: 0.2.3
Summary: Bot helpers for Automa
Author-email: "Sunkara, Inc." <engineering@automa.app>
License-Expression: MIT
Project-URL: Homepage, https://automa.app
Project-URL: Repository, https://github.com/automa/sdk-python
Classifier: Intended Audience :: Developers
Classifier: Programming Language :: Python :: 3.11
Classifier: Programming Language :: Python :: 3.12
Classifier: Typing :: Typed
Requires-Python: >=3.11
Requires-Dist: anyio<5,>=3.5.0
Requires-Dist: httpx~=0.23
Requires-Dist: typing-extensions~=4.10
